alchemiscale/__init__.py
alchemiscale/cli.py
alchemiscale/cli_utils.py
alchemiscale/compression.py
alchemiscale/models.py
alchemiscale/settings.py
alchemiscale/utils.py
alchemiscale/validators.py
alchemiscale/base/__init__.py
alchemiscale/base/api.py
alchemiscale/base/client.py
alchemiscale/compute/__init__.py
alchemiscale/compute/api.py
alchemiscale/compute/client.py
alchemiscale/compute/manager.py
alchemiscale/compute/service.py
alchemiscale/compute/settings.py
alchemiscale/interface/__init__.py
alchemiscale/interface/api.py
alchemiscale/interface/client.py
alchemiscale/migrations/v03_to_v04.py
alchemiscale/security/__init__.py
alchemiscale/security/auth.py
alchemiscale/security/models.py
alchemiscale/storage/__init__.py
alchemiscale/storage/cypher.py
alchemiscale/storage/models.py
alchemiscale/storage/objectstore.py
alchemiscale/storage/statestore.py
alchemiscale/storage/subgraph.py
alchemiscale/strategist/__init__.py
alchemiscale/strategist/service.py
alchemiscale/strategist/settings.py
alchemiscale/tests/__init__.py
alchemiscale/tests/integration/__init__.py
alchemiscale/tests/integration/conftest.py
alchemiscale/tests/integration/test_cli.py
alchemiscale/tests/integration/utils.py
alchemiscale/tests/integration/compute/__init__.py
alchemiscale/tests/integration/compute/conftest.py
alchemiscale/tests/integration/compute/test_compute_api.py
alchemiscale/tests/integration/compute/utils.py
alchemiscale/tests/integration/compute/client/__init__.py
alchemiscale/tests/integration/compute/client/conftest.py
alchemiscale/tests/integration/compute/client/test_compute_client.py
alchemiscale/tests/integration/compute/client/test_compute_manager.py
alchemiscale/tests/integration/compute/client/test_compute_manager_client.py
alchemiscale/tests/integration/compute/client/test_compute_service.py
alchemiscale/tests/integration/interface/__init__.py
alchemiscale/tests/integration/interface/conftest.py
alchemiscale/tests/integration/interface/test_api.py
alchemiscale-0.7.2.dist-info/licenses/LICENSE
alchemiscale-0.7.2.dist-info/METADATA
alchemiscale-0.7.2.dist-info/WHEEL
alchemiscale-0.7.2.dist-info/entry_points.txt
alchemiscale-0.7.2.dist-info/top_level.txt
alchemiscale-0.7.2.dist-info/RECORD
