Metadata-Version: 2.4
Name: alchemiscale
Version: 0.7.2
Summary: a high-throughput alchemical free energy execution system for use with HPC, cloud, bare metal, and Folding@Home
Author: OpenFE and OpenFF developers
License-Expression: MIT
Project-URL: Homepage, https://github.com/OpenFreeEnergy/alchemiscale
Classifier: Development Status :: 4 - Beta
Classifier: Intended Audience :: Science/Research
Classifier: Operating System :: POSIX
Classifier: Programming Language :: Python :: 3
Classifier: Topic :: Scientific/Engineering :: Bio-Informatics
Classifier: Topic :: Scientific/Engineering :: Chemistry
Requires-Python: >=3.10
License-File: LICENSE
Provides-Extra: test
Requires-Dist: pytest; extra == "test"
Requires-Dist: pytest-xdist; extra == "test"
Dynamic: license-file
